Workbook

Sheet input
B2: Information declared in prior year (2024) | G2: Detail in the 'Description' field
B3: date | C3: event | D3: declared_quantity | E3: declared_avg_price_brl | F3: position_2024_12_31_brl | G3: avg_cost_usd | H3: total_cost_usd
B4: 45657 | C4: Saldo inicial | F4: =E4*D4 | H4: =G4*D4
B6: Vesting of RSUs — totals by release date (auto-computed from the per-grant detail below)
B7: release_date | C7: event | D7: quantity_released | E7: share_closing_price_usd | F7: fx_rate_brl_usd_ptax_sell | G7: share_value_brl | H7: total_value_brl
B8: 45660 | C8: Vesting | D8: =SUMIFS($E$30:$E$45,$B$30:$B$45,B8) | E8: =IFERROR(INDEX($F$30:$F$45,MATCH(B8,$B$30:$B$45,0)),0) | F8: {=IFERROR(XLOOKUP(B8,aux_ptax_historical_data!B:B,aux_ptax_historical_data!E:E),"")} | G8: =ROUND(E8*F8,2) | H8: =D8*G8
B9: 45748 | C9: Vesting | D9: =SUMIFS($E$30:$E$45,$B$30:$B$45,B9) | E9: =IFERROR(INDEX($F$30:$F$45,MATCH(B9,$B$30:$B$45,0)),0) | F9: {=IFERROR(XLOOKUP(B9,aux_ptax_historical_data!B:B,aux_ptax_historical_data!E:E),"")} | G9: =ROUND(E9*F9,2) | H9: =D9*G9
B10: 45839 | C10: Vesting | D10: =SUMIFS($E$30:$E$45,$B$30:$B$45,B10) | E10: =IFERROR(INDEX($F$30:$F$45,MATCH(B10,$B$30:$B$45,0)),0) | F10: {=IFERROR(XLOOKUP(B10,aux_ptax_historical_data!B:B,aux_ptax_historical_data!E:E),"")} | G10: =ROUND(E10*F10,2) | H10: =D10*G10
B11: 45931 | C11: Vesting | D11: =SUMIFS($E$30:$E$45,$B$30:$B$45,B11) | E11: =IFERROR(INDEX($F$30:$F$45,MATCH(B11,$B$30:$B$45,0)),0) | F11: {=IFERROR(XLOOKUP(B11,aux_ptax_historical_data!B:B,aux_ptax_historical_data!E:E),"")} | G11: =ROUND(E11*F11,2) | H11: =D11*G11
B12: total | D12: =SUM(D8:D11) | H12: =SUM(H8:H11)
B14: Sale of shares (if applicable)
B15: date | C15: event | D15: quantity_sold | E15: sale_price_usd | F15: fx_rate_brl_usd_ptax_buy | G15: share_value_brl | H15: total_value_brl
C16: =IF(B16="","","Venda") | F16: {=IFERROR(XLOOKUP(B16,aux_ptax_historical_data!B:B,aux_ptax_historical_data!D:D),"")} | G16: =IF(B16="","",ROUND(E16*F16,2)) | H16: =IF(B16="","",D16*G16)
C17: =IF(B17="","","Venda") | F17: {=IFERROR(XLOOKUP(B17,aux_ptax_historical_data!B:B,aux_ptax_historical_data!D:D),"")} | G17: =IF(B17="","",ROUND(E17*F17,2)) | H17: =IF(B17="","",D17*G17)
C18: =IF(B18="","","Venda") | F18: {=IFERROR(XLOOKUP(B18,aux_ptax_historical_data!B:B,aux_ptax_historical_data!D:D),"")} | G18: =IF(B18="","",ROUND(E18*F18,2)) | H18: =IF(B18="","",D18*G18)
C19: =IF(B19="","","Venda") | F19: {=IFERROR(XLOOKUP(B19,aux_ptax_historical_data!B:B,aux_ptax_historical_data!D:D),"")} | G19: =IF(B19="","",ROUND(E19*F19,2)) | H19: =IF(B19="","",D19*G19)
C20: =IF(B20="","","Venda") | F20: {=IFERROR(XLOOKUP(B20,aux_ptax_historical_data!B:B,aux_ptax_historical_data!D:D),"")} | G20: =IF(B20="","",ROUND(E20*F20,2)) | H20: =IF(B20="","",D20*G20)
F21: {=IFERROR(XLOOKUP(B21,aux_ptax_historical_data!B:B,aux_ptax_historical_data!D:D),"")} | G21: =IF(B21="","",ROUND(E21*F21,2)) | H21: =IF(B21="","",D21*G21)
F22: {=IFERROR(XLOOKUP(B22,aux_ptax_historical_data!B:B,aux_ptax_historical_data!D:D),"")} | G22: =IF(B22="","",ROUND(E22*F22,2)) | H22: =IF(B22="","",D22*G22)
C23: =IF(B23="","","Venda") | F23: {=IFERROR(XLOOKUP(B23,aux_ptax_historical_data!B:B,aux_ptax_historical_data!D:D),"")} | G23: =IF(B23="","",ROUND(E23*F23,2)) | H23: =IF(B23="","",D23*G23)
C24: =IF(B24="","","Venda") | F24: {=IFERROR(XLOOKUP(B24,aux_ptax_historical_data!B:B,aux_ptax_historical_data!D:D),"")} | G24: =IF(B24="","",ROUND(E24*F24,2)) | H24: =IF(B24="","",D24*G24)
C25: =IF(B25="","","Venda") | F25: {=IFERROR(XLOOKUP(B25,aux_ptax_historical_data!B:B,aux_ptax_historical_data!D:D),"")} | G25: =IF(B25="","",ROUND(E25*F25,2)) | H25: =IF(B25="","",D25*G25)
B26: total | D26: =SUM(D16:D25) | H26: =SUM(H16:H25)
B28: Vesting detail — enter one row per grant (release_date, award_date, award_number, net quantity, closing price)
B29: release_date | C29: award_date | D29: award_number | E29: net_quantity | F29: closing_price_usd

Sheet do_not_change__calculation_memo
B2: Cálculo de ganho/perda de capital (se aplicável) | K2: quantity | O2: amount_brl | S2: amount_usd
B3: date | C3: event | D3: quantity_vested_sold | E3: vesting_sale_price_usd | F3: fx_rate_brl_usd | G3: share_value_brl | H3: total_value_brl | I3: avg_price_to_date_brl | J3: gain_loss_brl | K3: initial | L3: in | M3: out | N3: net | O3: initial | P3: in | Q3: out | R3: net | S3: initial | T3: in | U3: out | V3: net
B4: =IFERROR(__xludf.DUMMYFUNCTION("SORT(FILTER( { input!B8:E11; input!B16:E25 }, { input!E8:E11; input!E16:E25 } <> 0 ))"),45660.0) | C4: =IFERROR(__xludf.DUMMYFUNCTION("""COMPUTED_VALUE"""),"Vesting") | E4: =IFERROR(__xludf.DUMMYFUNCTION("""COMPUTED_VALUE"""),10.63) | F4: =IFERROR(VLOOKUP(B4,aux_ptax_historical_data!$B:$E,4,0),"") | G4: =IFERROR(E4*F4,"") | H4: =IFERROR(G4*D4,"") | I4: =IFERROR(O4/K4,0) | J4: =IFERROR(IF(C4="Vesting",0,H4-Q4),0) | K4: =input!$D$4 | L4: =IF(C4="Vesting",D4,0) | M4: =IF(C4="Venda",D4,0) | N4: =K4+L4-M4 | O4: =input!$F$4 | P4: =IF(C4="Vesting",H4,0) | Q4: =IF(C4="Venda",O4*M4/K4,0) | R4: =O4+P4-Q4 | S4: =input!$H$4 | T4: =IF(C4="Vesting",D4*E4,0) | U4: =IF(C4="Venda",S4*M4/K4,0) | V4: =S4+T4-U4
B5: =IFERROR(__xludf.DUMMYFUNCTION("""COMPUTED_VALUE"""),45748.0) | C5: =IFERROR(__xludf.DUMMYFUNCTION("""COMPUTED_VALUE"""),"Vesting") | E5: =IFERROR(__xludf.DUMMYFUNCTION("""COMPUTED_VALUE"""),10.43) | F5: =IFERROR(VLOOKUP(B5,aux_ptax_historical_data!$B:$E,4,0),"") | G5: =IFERROR(E5*F5,"") | H5: =IFERROR(G5*D5,"") | I5: =IFERROR(O5/K5,0) | J5: =IFERROR(IF(C5="Vesting",0,H5-Q5),0) | K5: =K4+L4-M4 | L5: =IF(C5="Vesting",D5,0) | M5: =IF(C5="Venda",D5,0) | N5: =K5+L5-M5 | O5: =R4 | P5: =IF(C5="Vesting",H5,0) | Q5: =IF(C5="Venda",O5*M5/K5,0) | R5: =O5+P5-Q5 | S5: =V4 | T5: =IF(C5="Vesting",D5*E5,0) | U5: =IF(C5="Venda",S5*M5/K5,0) | V5: =S5+T5-U5
B6: =IFERROR(__xludf.DUMMYFUNCTION("""COMPUTED_VALUE"""),45839.0) | C6: =IFERROR(__xludf.DUMMYFUNCTION("""COMPUTED_VALUE"""),"Vesting") | E6: =IFERROR(__xludf.DUMMYFUNCTION("""COMPUTED_VALUE"""),13.64) | F6: =IFERROR(VLOOKUP(B6,aux_ptax_historical_data!$B:$E,4,0),"") | G6: =IFERROR(E6*F6,"") | H6: =IFERROR(G6*D6,"") | I6: =IFERROR(O6/K6,0) | J6: =IFERROR(IF(C6="Vesting",0,H6-Q6),0) | K6: =K5+L5-M5 | L6: =IF(C6="Vesting",D6,0) | M6: =IF(C6="Venda",D6,0) | N6: =K6+L6-M6 | O6: =R5 | P6: =IF(C6="Vesting",H6,0) | Q6: =IF(C6="Venda",O6*M6/K6,0) | R6: =O6+P6-Q6 | S6: =V5 | T6: =IF(C6="Vesting",D6*E6,0) | U6: =IF(C6="Venda",S6*M6/K6,0) | V6: =S6+T6-U6
B7: =IFERROR(__xludf.DUMMYFUNCTION("""COMPUTED_VALUE"""),45931.0) | C7: =IFERROR(__xludf.DUMMYFUNCTION("""COMPUTED_VALUE"""),"Vesting") | E7: =IFERROR(__xludf.DUMMYFUNCTION("""COMPUTED_VALUE"""),15.19) | F7: =IFERROR(VLOOKUP(B7,aux_ptax_historical_data!$B:$E,4,0),"") | G7: =IFERROR(E7*F7,"") | H7: =IFERROR(G7*D7,"") | I7: =IFERROR(O7/K7,0) | J7: =IFERROR(IF(C7="Vesting",0,H7-Q7),0) | K7: =K6+L6-M6 | L7: =IF(C7="Vesting",D7,0) | M7: =IF(C7="Venda",D7,0) | N7: =K7+L7-M7 | O7: =R6 | P7: =IF(C7="Vesting",H7,0) | Q7: =IF(C7="Venda",O7*M7/K7,0) | R7: =O7+P7-Q7 | S7: =V6 | T7: =IF(C7="Vesting",D7*E7,0) | U7: =IF(C7="Venda",S7*M7/K7,0) | V7: =S7+T7-U7
F8: =IFERROR(VLOOKUP(B8,aux_ptax_historical_data!$B:$E,4,0),"") | G8: =IFERROR(E8*F8,"") | H8: =IFERROR(G8*D8,"") | I8: =IFERROR(O8/K8,0) | J8: =IFERROR(IF(C8="Vesting",0,H8-Q8),0) | K8: =K7+L7-M7 | L8: =IF(C8="Vesting",D8,0) | M8: =IF(C8="Venda",D8,0) | N8: =K8+L8-M8 | O8: =R7 | P8: =IF(C8="Vesting",H8,0) | Q8: =IF(C8="Venda",O8*M8/K8,0) | R8: =O8+P8-Q8 | S8: =V7 | T8: =IF(C8="Vesting",D8*E8,0) | U8: =IF(C8="Venda",S8*M8/K8,0) | V8: =S8+T8-U8
F9: =IFERROR(VLOOKUP(B9,aux_ptax_historical_data!$B:$E,4,0),"") | G9: =IFERROR(E9*F9,"") | H9: =IFERROR(G9*D9,"") | I9: =IFERROR(O9/K9,0) | J9: =IFERROR(IF(C9="Vesting",0,H9-Q9),0) | K9: =K8+L8-M8 | L9: =IF(C9="Vesting",D9,0) | M9: =IF(C9="Venda",D9,0) | N9: =K9+L9-M9 | O9: =R8 | P9: =IF(C9="Vesting",H9,0) | Q9: =IF(C9="Venda",O9*M9/K9,0) | R9: =O9+P9-Q9 | S9: =V8 | T9: =IF(C9="Vesting",D9*E9,0) | U9: =IF(C9="Venda",S9*M9/K9,0) | V9: =S9+T9-U9
F10: =IFERROR(VLOOKUP(B10,aux_ptax_historical_data!$B:$E,4,0),"") | G10: =IFERROR(E10*F10,"") | H10: =IFERROR(G10*D10,"") | I10: =IFERROR(O10/K10,0) | J10: =IFERROR(IF(C10="Vesting",0,H10-Q10),0) | K10: =K9+L9-M9 | L10: =IF(C10="Vesting",D10,0) | M10: =IF(C10="Venda",D10,0) | N10: =K10+L10-M10 | O10: =R9 | P10: =IF(C10="Vesting",H10,0) | Q10: =IF(C10="Venda",O10*M10/K10,0) | R10: =O10+P10-Q10 | S10: =V9 | T10: =IF(C10="Vesting",D10*E10,0) | U10: =IF(C10="Venda",S10*M10/K10,0) | V10: =S10+T10-U10
F11: =IFERROR(VLOOKUP(B11,aux_ptax_historical_data!$B:$E,4,0),"") | G11: =IFERROR(E11*F11,"") | H11: =IFERROR(G11*D11,"") | I11: =IFERROR(O11/K11,0) | J11: =IFERROR(IF(C11="Vesting",0,H11-Q11),0) | K11: =K10+L10-M10 | L11: =IF(C11="Vesting",D11,0) | M11: =IF(C11="Venda",D11,0) | N11: =K11+L11-M11 | O11: =R10 | P11: =IF(C11="Vesting",H11,0) | Q11: =IF(C11="Venda",O11*M11/K11,0) | R11: =O11+P11-Q11 | S11: =V10 | T11: =IF(C11="Vesting",D11*E11,0) | U11: =IF(C11="Venda",S11*M11/K11,0) | V11: =S11+T11-U11
F12: =IFERROR(VLOOKUP(B12,aux_ptax_historical_data!$B:$E,4,0),"") | G12: =IFERROR(E12*F12,"") | H12: =IFERROR(G12*D12,"") | I12: =IFERROR(O12/K12,0) | J12: =IFERROR(IF(C12="Vesting",0,H12-Q12),0) | K12: =K11+L11-M11 | L12: =IF(C12="Vesting",D12,0) | M12: =IF(C12="Venda",D12,0) | N12: =K12+L12-M12 | O12: =R11 | P12: =IF(C12="Vesting",H12,0) | Q12: =IF(C12="Venda",O12*M12/K12,0) | R12: =O12+P12-Q12 | S12: =V11 | T12: =IF(C12="Vesting",D12*E12,0) | U12: =IF(C12="Venda",S12*M12/K12,0) | V12: =S12+T12-U12
F13: =IFERROR(VLOOKUP(B13,aux_ptax_historical_data!$B:$E,4,0),"") | G13: =IFERROR(E13*F13,"") | H13: =IFERROR(G13*D13,"") | I13: =IFERROR(O13/K13,0) | J13: =IFERROR(IF(C13="Vesting",0,H13-Q13),0) | K13: =K12+L12-M12 | L13: =IF(C13="Vesting",D13,0) | M13: =IF(C13="Venda",D13,0) | N13: =K13+L13-M13 | O13: =R12 | P13: =IF(C13="Vesting",H13,0) | Q13: =IF(C13="Venda",O13*M13/K13,0) | R13: =O13+P13-Q13 | S13: =V12 | T13: =IF(C13="Vesting",D13*E13,0) | U13: =IF(C13="Venda",S13*M13/K13,0) | V13: =S13+T13-U13
F14: =IFERROR(VLOOKUP(B14,aux_ptax_historical_data!$B:$E,4,0),"") | G14: =IFERROR(E14*F14,"") | H14: =IFERROR(G14*D14,"") | I14: =IFERROR(O14/K14,0) | J14: =IFERROR(IF(C14="Vesting",0,H14-Q14),0) | K14: =K13+L13-M13 | L14: =IF(C14="Vesting",D14,0) | M14: =IF(C14="Venda",D14,0) | N14: =K14+L14-M14 | O14: =R13 | P14: =IF(C14="Vesting",H14,0) | Q14: =IF(C14="Venda",O14*M14/K14,0) | R14: =O14+P14-Q14 | S14: =V13 | T14: =IF(C14="Vesting",D14*E14,0) | U14: =IF(C14="Venda",S14*M14/K14,0) | V14: =S14+T14-U14
F15: =IFERROR(VLOOKUP(B15,aux_ptax_historical_data!$B:$E,4,0),"") | G15: =IFERROR(E15*F15,"") | H15: =IFERROR(G15*D15,"") | I15: =IFERROR(O15/K15,0) | J15: =IFERROR(IF(C15="Vesting",0,H15-Q15),0) | K15: =K14+L14-M14 | L15: =IF(C15="Vesting",D15,0) | M15: =IF(C15="Venda",D15,0) | N15: =K15+L15-M15 | O15: =R14 | P15: =IF(C15="Vesting",H15,0) | Q15: =IF(C15="Venda",O15*M15/K15,0) | R15: =O15+P15-Q15 | S15: =V14 | T15: =IF(C15="Vesting",D15*E15,0) | U15: =IF(C15="Venda",S15*M15/K15,0) | V15: =S15+T15-U15
F16: =IFERROR(VLOOKUP(B16,aux_ptax_historical_data!$B:$E,4,0),"") | G16: =IFERROR(E16*F16,"") | H16: =IFERROR(G16*D16,"") | I16: =IFERROR(O16/K16,0) | J16: =IFERROR(IF(C16="Vesting",0,H16-Q16),0) | K16: =K15+L15-M15 | L16: =IF(C16="Vesting",D16,0) | M16: =IF(C16="Venda",D16,0) | N16: =K16+L16-M16 | O16: =R15 | P16: =IF(C16="Vesting",H16,0) | Q16: =IF(C16="Venda",O16*M16/K16,0) | R16: =O16+P16-Q16 | S16: =V15 | T16: =IF(C16="Vesting",D16*E16,0) | U16: =IF(C16="Venda",S16*M16/K16,0) | V16: =S16+T16-U16
F17: =IFERROR(VLOOKUP(B17,aux_ptax_historical_data!$B:$E,4,0),"") | G17: =IFERROR(E17*F17,"") | H17: =IFERROR(G17*D17,"") | I17: =IFERROR(O17/K17,0) | J17: =IFERROR(IF(C17="Vesting",0,H17-Q17),0) | K17: =K16+L16-M16 | L17: =IF(C17="Vesting",D17,0) | M17: =IF(C17="Venda",D17,0) | N17: =K17+L17-M17 | O17: =R16 | P17: =IF(C17="Vesting",H17,0) | Q17: =IF(C17="Venda",O17*M17/K17,0) | R17: =O17+P17-Q17 | S17: =V16 | T17: =IF(C17="Vesting",D17*E17,0) | U17: =IF(C17="Venda",S17*M17/K17,0) | V17: =S17+T17-U17

Sheet aux_ptax_historical_data
B2: date | C2: currency | D2: ptax_buy | E2: ptax_sell
B3: 45293 | C3: USD | D3: 4.891 | E3: 4.8916
B4: 45294 | C4: USD | D4: 4.9206 | E4: 4.9212
B5: 45295 | C5: USD | D5: 4.9182 | E5: 4.9188
B6: 45296 | C6: USD | D6: 4.8893 | E6: 4.8899
B7: 45299 | C7: USD | D7: 4.8844 | E7: 4.885
B8: 45300 | C8: USD | D8: 4.8931 | E8: 4.8937
B9: 45301 | C9: USD | D9: 4.8895 | E9: 4.8901
B10: 45302 | C10: USD | D10: 4.8788 | E10: 4.8794
B11: 45303 | C11: USD | D11: 4.8537 | E11: 4.8543
B12: 45306 | C12: USD | D12: 4.8759 | E12: 4.8765
B13: 45307 | C13: USD | D13: 4.9032 | E13: 4.9038
B14: 45308 | C14: USD | D14: 4.934 | E14: 4.9346
... B507: 46022 | C507: USD | D507: 5.5018 | E507: 5.5024

Sheet output
B2: Capital gain/loss calculation (if applicable)
B3: date | C3: event | D3: quantity_sold | E3: avg_price_to_date_brl | F3: share_value_brl | G3: gain_loss_brl
B4: =input!B16 | C4: =IF(B4="","", "Cálculo") | D4: =input!D16 | E4: {=IFERROR(INDEX(do_not_change__calculation_memo!$I$4:$I$17,MATCH(1,(do_not_change__calculation_memo!$B$4:$B$17=B4)*(do_not_change__calculation_memo!$C$4:$C$17="Venda"),0)),"")} | F4: =input!G16 | G4: =IFERROR(IF(B4="","",D4*F4-D4*E4),0)
B5: =input!B17 | C5: =IF(B5="","", "Cálculo") | D5: =input!D17 | E5: {=IFERROR(INDEX(do_not_change__calculation_memo!$I$4:$I$17,MATCH(1,(do_not_change__calculation_memo!$B$4:$B$17=B5)*(do_not_change__calculation_memo!$C$4:$C$17="Venda"),0)),"")} | F5: =input!G17 | G5: =IFERROR(IF(B5="","",D5*F5-D5*E5),0)
B6: =input!B18 | C6: =IF(B6="","", "Cálculo") | D6: =input!D18 | E6: {=IFERROR(INDEX(do_not_change__calculation_memo!$I$4:$I$17,MATCH(1,(do_not_change__calculation_memo!$B$4:$B$17=B6)*(do_not_change__calculation_memo!$C$4:$C$17="Venda"),0)),"")} | F6: =input!G18 | G6: =IFERROR(IF(B6="","",D6*F6-D6*E6),0)
B7: =input!B19 | C7: =IF(B7="","", "Cálculo") | D7: =input!D19 | E7: {=IFERROR(INDEX(do_not_change__calculation_memo!$I$4:$I$17,MATCH(1,(do_not_change__calculation_memo!$B$4:$B$17=B7)*(do_not_change__calculation_memo!$C$4:$C$17="Venda"),0)),"")} | F7: =input!G19 | G7: =IFERROR(IF(B7="","",D7*F7-D7*E7),0)
B8: =input!B20 | C8: =IF(B8="","", "Cálculo") | D8: =input!D20 | E8: {=IFERROR(INDEX(do_not_change__calculation_memo!$I$4:$I$17,MATCH(1,(do_not_change__calculation_memo!$B$4:$B$17=B8)*(do_not_change__calculation_memo!$C$4:$C$17="Venda"),0)),"")} | F8: =input!G20 | G8: =IFERROR(IF(B8="","",D8*F8-D8*E8),0)
B9: =input!B21 | C9: =IF(B9="","", "Cálculo") | D9: =input!D21 | E9: {=IFERROR(INDEX(do_not_change__calculation_memo!$I$4:$I$17,MATCH(1,(do_not_change__calculation_memo!$B$4:$B$17=B9)*(do_not_change__calculation_memo!$C$4:$C$17="Venda"),0)),"")} | F9: =input!G21 | G9: =IFERROR(IF(B9="","",D9*F9-D9*E9),0)
B10: =input!B22 | C10: =IF(B10="","", "Cálculo") | D10: =input!D22 | E10: {=IFERROR(INDEX(do_not_change__calculation_memo!$I$4:$I$17,MATCH(1,(do_not_change__calculation_memo!$B$4:$B$17=B10)*(do_not_change__calculation_memo!$C$4:$C$17="Venda"),0)),"")} | F10: =input!G22 | G10: =IFERROR(IF(B10="","",D10*F10-D10*E10),0)
B11: =input!B23 | C11: =IF(B11="","", "Cálculo") | D11: =input!D23 | E11: {=IFERROR(INDEX(do_not_change__calculation_memo!$I$4:$I$17,MATCH(1,(do_not_change__calculation_memo!$B$4:$B$17=B11)*(do_not_change__calculation_memo!$C$4:$C$17="Venda"),0)),"")} | F11: =input!G23 | G11: =IFERROR(IF(B11="","",D11*F11-D11*E11),0)
B12: =input!B24 | C12: =IF(B12="","", "Cálculo") | D12: =input!D24 | E12: {=IFERROR(INDEX(do_not_change__calculation_memo!$I$4:$I$17,MATCH(1,(do_not_change__calculation_memo!$B$4:$B$17=B12)*(do_not_change__calculation_memo!$C$4:$C$17="Venda"),0)),"")} | F12: =input!G24 | G12: =IFERROR(IF(B12="","",D12*F12-D12*E12),0)
B13: =input!B25 | C13: =IF(B13="","", "Cálculo") | D13: =input!D25 | E13: {=IFERROR(INDEX(do_not_change__calculation_memo!$I$4:$I$17,MATCH(1,(do_not_change__calculation_memo!$B$4:$B$17=B13)*(do_not_change__calculation_memo!$C$4:$C$17="Venda"),0)),"")} | F13: =input!G25 | G13: =IFERROR(IF(B13="","",D13*F13-D13*E13),0)
B15: Information for current declaration (2025) - Assets and Rights | G15: Detalhe no campo 'Discriminação'
B16: date | C16: event | D16: final_quantity | E16: final_avg_price_brl | F16: position_2025_12_31_brl | G16: avg_cost_usd | H16: total_cost_usd
B17: 46022 | C17: Cálculo | D17: {=INDEX(do_not_change__calculation_memo!$N$4:$N$17,MATCH(B17,do_not_change__calculation_memo!$B$4:$B$17,1))} | E17: =F17/D17 | F17: {=INDEX(do_not_change__calculation_memo!$R$4:$R$17,MATCH(B17,do_not_change__calculation_memo!$B$4:$B$17,1))} | G17: =H17/D17 | H17: {=INDEX(do_not_change__calculation_memo!$V$4:$V$17,MATCH(B17,do_not_change__calculation_memo!$B$4:$B$17,1))}
B19: Capital gain assessment (in case of sale)
B20: total_profit_or_loss_brl
B21: =SUM($G$4:$G$13)
